doniclient/__init__.py
doniclient/osc/__init__.py
doniclient/osc/availability.py
doniclient/osc/cli.py
doniclient/osc/common.py
doniclient/osc/plugin.py
doniclient/tests/__init__.py
doniclient/tests/osc/__init__.py
doniclient/tests/osc/fakes.py
doniclient/tests/osc/test_hardware.py
doniclient/tests/v1/__init__.py
doniclient/v1/client.py
doniclient/v1/resource_fields.py
python_doniclient-1.0.3.dist-info/entry_points.txt
python_doniclient-1.0.3.dist-info/WHEEL
python_doniclient-1.0.3.dist-info/METADATA
python_doniclient-1.0.3.dist-info/RECORD
